{
  "case_creation_details":{
    "case_type_id":"A58",
    "event_id":"create-case-adop-bs",
    "case_data":{
      "witnessWelshLanguagePreference":"Written",
      "respondentRequireInterpreter":"Yes",
      "welshPreferencePartyName":"partyName",
      "courtInterpreterAssistanceLanguage":"Spanish",
      "scannedDocuments":[
        {
          "value":{
            "document_url":"http://dm-store:8080/documents/0663b907-eac5-443a-8117-62f1fd67fc5c",
            "document_filename":"test.pdf",
            "document_binary_url":"http://dm-store:8080/documents/0663b907-eac5-443a-8117-62f1fd67fc5c/binary"
          }
        }
      ],
      "courtpreferredDates":"11/10/2022,21/10/2022",
      "applicantMaritalStatus":"",
      "birthFatherOccupation":"fatherOccupation",
      "applicantRequireInterpreter":"Yes",
      "applicant2FirstName":null,
      "birthMotherFirstName":"motherFirstName",
      "applicant2StatementOfTruth":null,
      "otherParentRelationshipToChild":"Father",
      "parentalResponsibility":"No",
      "courtUnavailableDates":"10/10/2022,20/10/2022",
      "applicant1RelationToChild":null,
      "applicant1Occupation":null,
      "applicant1Signing":"true",
      "applicant1StatementOfTruthDate":"12/12/2000",
      "specialAssistanceFacilitiesRequired":"Yes",
      "solicitor":{
        "solicitorName":"SolName",
        "solicitorFirm":"SolFirmName",
        "solicitorAddress":"123, Address Tw31NN",
        "solicitorPhoneNumber":"+447438766833",
        "solicitorFaxNumber":null,
        "solicitorDxNumber":null,
        "solicitorEmail":"test@test.com",
        "solicitorFeeAccountNumber":"12345667899"
      },
      "applicant1FirstName":"Test First Name",
      "childWelshLanguagePreference":"Both",
      "applicant1TelephoneNumber":"+447438766833",
      "birthFatherLastName":"fatherFirstName",
      "otherPartyRequireInterpreter":"Yes",
      "birthFatherNationality":"fatherNationality",
      "applicantRelationToChild":"",
      "applicant2RelationToChild":null,
      "applicant1LastName":"Test Last Name",
      "applicant1DateOfBirth":null,
      "applicant2TelephoneNumber":null,
      "specialAssistanceFacilities":"WheelChair",
      "guardianFirstName":"guardianFirstName",
      "applicant2DateOfBirth":null,
      "birthFatherFirstName":"Address1 London",
      "applicantsDomicileStatus":"true",
      "applicantRelationToChildFatherPartner":"",
      "applicant1SignStatementOfTruth":"true",
      "applicant1LegalRepSignature":"true",
      "applicant2Nationality":null,
      "applicant2LegalRepPosition":null,
      "birthMotherAddress":"motherAddress",
      "childrenAdoptionPaymentDetails":null,
      "guardianLastName":"guardianLastName",
      "welshSpokenInCourtRequired":"Yes",
      "applicant1LegalRepFirm":null,
      "applicant1Address":"Male",
      "applicant2Address":null,
      "birthFatherAddress":"Address1 London",
      "applicant2LegalRepFirm":null,
      "welshPreferenceWitnessName":"witnessName",
      "applicant1StatementOfTruth":"true",
      "applicant2LastName":null,
      "childrenHealthReportDate":null,
      "applicant1Nationality":"British",
      "applicant2SignStatementOfTruth":null,
      "childrenFirstNameAfterAdoption":"charlie",
      "childrenLastNameAfterAdoption":"impey",
      "applicant2Signing":null,
      "partyWelshLanguagePreference":"Spoken",
      "applicant1SotFullName":null,
      "birthMotherLastName":"motherLastName",
      "birthMotherNationality":"motherNationality",
      "parentalResponsibilityOrder":"Yes",
      "welshPreferenceChildName":"childName",
      "courtInterpreterAssistanceRequired":"Yes",
      "guardianAddress":"Address1 London",
      "applicant2Occupation":null,
      "applicant1LegalRepPosition":null,
      "birthMotherOccupation":"motherOccupation",
      "applicant2SotFullName":null,
      "applicant2LegalRepSignature":null,
      "otherPartyName":"otherPartyName"
    }
  },
  "warnings":[

  ]
}