{
  "ocr_data_fields":[
    {
      "name":"applicant1_firstName",
      "value":"applicant1_firstName"
    },
    {
      "name":"applicant1_lastName",
      "value":"applicant1_lastName"
    },
    {
      "name":"applicant1_telephoneNumber",
      "value":null
    },
    {
      "name":"applicant1_address",
      "value":null
    },
    {
      "name":"applicant2_firstName",
      "value":"applicant2_firstName"
    },
    {
      "name":"applicant2_lastName",
      "value":"applicant2_lastName"
    },
    {
      "name":"applicant2_telephoneNumber",
      "value":"09999999990"
    },
    {
      "name":"applicant2_address",
      "value":"123 test street, London"
    },
    {
      "name": "adoption_order_consent",
      "value": "true"
    },
    {
      "name": "adoption_order_consent_advance",
      "value": "true"
    },
    {
      "name": "adoption_order_consent_agency",
      "value": "true"
    },
    {
      "name": "adoption_order_no_consent",
      "value": "true"
    },
    {
       "name": "court_consent_parent_not_found",
       "value": "true"
    },
    {
       "name": "court_consent_parent_lack_capacity",
       "value": "true"
    },
    {
       "name": "court_consent_child_welfare",
       "value": "true"
    }
  ],
  "form_type": "A58"
}
